easy_differ/__init__.py
easy_differ/easy_differ.py
easy_differ-0.2.1.dist-info/LICENSE
easy_differ-0.2.1.dist-info/METADATA
easy_differ-0.2.1.dist-info/WHEEL
easy_differ-0.2.1.dist-info/top_level.txt
easy_differ-0.2.1.dist-info/RECORD
