Metadata-Version: 2.1
Name: easy-differ
Version: 0.2.1
Summary: Compare Text line by line. See different text and their lines
Home-page: https://github.com/FurkanOzkaya/easy_differ
Author: Furkan Ozkaya
Author-email: furkanozkaya45@gmail.com
License: MIT
Download-URL: https://github.com/FurkanOzkaya/easy_differ/archive/0.2.1.tar.gz
Keywords: DIFFER,COMPARE,TEXT COMPARE,ARRAY COMPARE
Platform: UNKNOWN
Classifier: Development Status :: 3 - Alpha
Classifier: Intended Audience :: Developers
Classifier: Topic :: Software Development :: Build Tools
Classifier: License :: OSI Approved :: MIT License
Classifier: Programming Language :: Python :: 3
Classifier: Programming Language :: Python :: 3.4
Classifier: Programming Language :: Python :: 3.5
Classifier: Programming Language :: Python :: 3.6
Classifier: Programming Language :: Python :: 3.7
Classifier: Programming Language :: Python :: 3.8
